{"stats":{"minecraft:used":{"minecraft:carrot_on_a_stick":269,"minecraft:written_book":1},"minecraft:custom":{"minecraft:jump":323,"minecraft:time_since_rest":71298,"minecraft:damage_dealt":0,"minecraft:minecart_one_cm":2475105,"minecraft:damage_taken":94,"minecraft:crouch_one_cm":2261,"minecraft:leave_game":2,"minecraft:sprint_one_cm":60477,"minecraft:play_time":71298,"minecraft:time_since_death":71298,"minecraft:walk_on_water_one_cm":493,"minecraft:walk_one_cm":66961,"minecraft:sneak_time":1077,"minecraft:total_world_time":71298,"minecraft:climb_one_cm":1291,"minecraft:talked_to_villager":1,"minecraft:fall_one_cm":241470,"minecraft:fly_one_cm":277356,"minecraft:damage_dealt_resisted":1004}},"DataVersion":3120}