{"stats":{"minecraft:used":{"minecraft:carrot_on_a_stick":73,"minecraft:written_book":2},"minecraft:custom":{"minecraft:jump":235,"minecraft:time_since_rest":32344,"minecraft:minecart_one_cm":1201158,"minecraft:damage_taken":10,"minecraft:crouch_one_cm":12,"minecraft:play_time":32344,"minecraft:leave_game":3,"minecraft:sprint_one_cm":41120,"minecraft:walk_on_water_one_cm":252,"minecraft:time_since_death":32344,"minecraft:walk_one_cm":25372,"minecraft:sneak_time":246,"minecraft:climb_one_cm":788,"minecraft:total_world_time":32344,"minecraft:fall_one_cm":131404,"minecraft:fly_one_cm":94684}},"DataVersion":3120}